mailer/__init__.py
mailer/config.py
mailer/mailer.py
mailer/minifier.py
mailer/simple.py
mailer/utils.py
pyworks_mailer-0.0.1rc1.data/data/my_data/data_file
pyworks_mailer-0.0.1rc1.dist-info/LICENSE.txt
pyworks_mailer-0.0.1rc1.dist-info/METADATA
pyworks_mailer-0.0.1rc1.dist-info/WHEEL
pyworks_mailer-0.0.1rc1.dist-info/entry_points.txt
pyworks_mailer-0.0.1rc1.dist-info/top_level.txt
pyworks_mailer-0.0.1rc1.dist-info/RECORD
