Metadata-Version: 2.1
Name: pyworks-mailer
Version: 0.0.1rc1
Summary: PyWork Mailer provide fast way to use SMTP mail and the most email templates.
Home-page: https://github.com/pyworksasia/pyworks-mailer
Author: PyWorks Asia Team
Author-email: opensource@pyworks.asia
License: UNKNOWN
Project-URL: Bug Reports, https://github.com/pyworksasia/pyworks-mailer/issues
Project-URL: Funding, https://donate.pypi.org
Project-URL: Source, https://github.com/pyworksasia/pyworks-mailer/
Keywords: pyworks,smtp mail,mailer,mail templates
Platform: UNKNOWN
Classifier: Intended Audience :: Information Technology
Classifier: Intended Audience :: Developers
Classifier: Topic :: Internet
Classifier: Topic :: Software Development :: Libraries :: Application Frameworks
Classifier: Topic :: Software Development :: Libraries :: Python Modules
Classifier: Topic :: Software Development :: Libraries
Classifier: Topic :: Software Development
Classifier: Development Status :: 3 - Alpha
Classifier: License :: OSI Approved :: MIT License
Classifier: Programming Language :: Python :: 3.6
Classifier: Programming Language :: Python :: 3.7
Classifier: Programming Language :: Python :: 3.8
Classifier: Programming Language :: Python :: 3.9
Classifier: Programming Language :: Python :: 3 :: Only
Requires-Python: >=3.7, <4
Requires-Dist: htmlmin (==0.1.12)
Requires-Dist: jinja2 (==2.11.3)
Requires-Dist: python-dotenv (==0.15.0)
Requires-Dist: yagmail (==0.14.245)
Provides-Extra: dev
Requires-Dist: check-manifest ; extra == 'dev'
Provides-Extra: test
Requires-Dist: coverage ; extra == 'test'
